generalwords/__init__.py
generalwords/generalwords.py
generalwords-1.0.dist-info/DESCRIPTION.rst
generalwords-1.0.dist-info/METADATA
generalwords-1.0.dist-info/metadata.json
generalwords-1.0.dist-info/RECORD
generalwords-1.0.dist-info/top_level.txt
generalwords-1.0.dist-info/WHEEL
