Metadata-Version: 2.0
Name: generalwords
Version: 1.0
Summary: A somewhat curated collection of words to use in nonce generation.
Home-page: https://github.com/petrilli/generalwords
Author: Christopher Petrilli
Author-email: petrilli@amber.org
License: BSD Simplified
Keywords: generalwords
Platform: UNKNOWN
Classifier: Development Status :: 2 - Pre-Alpha
Classifier: Intended Audience :: Developers
Classifier: License :: OSI Approved :: BSD License
Classifier: Natural Language :: English
Classifier: Programming Language :: Python :: 2
Classifier: Programming Language :: Python :: 2.7
Classifier: Programming Language :: Python :: 3
Classifier: Programming Language :: Python :: 3.3
Classifier: Programming Language :: Python :: 3.4
